endpoints_proto_datastore/__init__.py
endpoints_proto_datastore/endpoints_proto_datastore_test_runner.py
endpoints_proto_datastore/test_utils.py
endpoints_proto_datastore/utils.py
endpoints_proto_datastore/utils_test.py
endpoints_proto_datastore/ndb/__init__.py
endpoints_proto_datastore/ndb/model.py
endpoints_proto_datastore/ndb/properties.py
endpoints_proto_datastore/ndb/utils.py
endpoints_proto_datastore-0.10.0.dist-info/DESCRIPTION.rst
endpoints_proto_datastore-0.10.0.dist-info/METADATA
endpoints_proto_datastore-0.10.0.dist-info/RECORD
endpoints_proto_datastore-0.10.0.dist-info/WHEEL
endpoints_proto_datastore-0.10.0.dist-info/metadata.json
endpoints_proto_datastore-0.10.0.dist-info/top_level.txt
