Metadata-Version: 2.0
Name: endpoints-proto-datastore
Version: 0.10.0
Summary: Google Cloud Endpoints Proto Datastore Library
Home-page: https://github.com/GoogleCloudPlatform/endpoints-proto-datastore
Author: Danny Hermes
Author-email: daniel.j.hermes@gmail.com
License: Apache
Platform: UNKNOWN
Classifier: Intended Audience :: Developers
Classifier: License :: OSI Approved :: Apache Software License
Classifier: Natural Language :: English
Classifier: Operating System :: OS Independent
Classifier: Programming Language :: Python
